apisamarinda/__init__.py
apisamarinda/api.py
apisamarinda-0.1.0.dist-info/METADATA
apisamarinda-0.1.0.dist-info/WHEEL
apisamarinda-0.1.0.dist-info/top_level.txt
apisamarinda-0.1.0.dist-info/RECORD
